gitreturn/__init__.py
gitreturn/bcolors.py
gitreturn/cli.py
gitreturn/exceptions.py
gitreturn/format.py
gitreturn/git.py
gitreturn/strings.py
gitreturn/trello.py
gitreturn-1.3.1.dist-info/entry_points.txt
gitreturn-1.3.1.dist-info/LICENSE
gitreturn-1.3.1.dist-info/WHEEL
gitreturn-1.3.1.dist-info/METADATA
gitreturn-1.3.1.dist-info/RECORD
