Metadata-Version: 2.1
Name: gitreturn
Version: 1.3.1
Summary: Script to return to staging.
License: MIT
Author: blackboardd
Author-email: brightenqtompkins@gmail.com
Requires-Python: >=3.7,<4.0
Classifier: License :: OSI Approved :: MIT License
Classifier: Programming Language :: Python :: 3
Classifier: Programming Language :: Python :: 3.10
Classifier: Programming Language :: Python :: 3.7
Classifier: Programming Language :: Python :: 3.8
Classifier: Programming Language :: Python :: 3.9
Requires-Dist: inquirerpy (>=0.3.3,<0.4.0)
Requires-Dist: requests (>=2.27.1,<3.0.0)
